<odoo>
    <record id="view_bol_config_settings" model="ir.ui.view">
        <field name="name">res.config.settings.view.form.bol</field>
        <field name="model">res.config.settings</field>
        <field name="inherit_id" ref="base.view_res_config_settings"/>
        <field name="arch" type="xml">
            <xpath expr="//div[@id='settings']" position="inside">
                <div class="app_settings_block" data-string="Bol.com Klantvragen">
                    <h2>Bol.com API-instellingen</h2>
                    <div class="row mt16 o_settings_container">
                        <div class="col-12 col-lg-6">
                            <field name="bol_client_id"/>
                            <field name="bol_client_secret"/>
                            <field name="bol_access_token"/>
                        </div>
                    </div>
                </div>
            </xpath>
        </field>
    </record>
</odoo>